rtests/__init__.py
rtests/rtests.py
rtests-0.1.6.dist-info/LICENSE
rtests-0.1.6.dist-info/METADATA
rtests-0.1.6.dist-info/WHEEL
rtests-0.1.6.dist-info/top_level.txt
rtests-0.1.6.dist-info/RECORD
